README.md
setup.py
AtomicP2P.egg-info/PKG-INFO
AtomicP2P.egg-info/SOURCES.txt
AtomicP2P.egg-info/dependency_links.txt
AtomicP2P.egg-info/requires.txt
AtomicP2P.egg-info/top_level.txt
atomic_p2p/__init__.py
atomic_p2p/__main__.py
atomic_p2p/local_monitor.py
atomic_p2p/abc/__init__.py
atomic_p2p/abc/authenticator.py
atomic_p2p/abc/topology.py
atomic_p2p/communication/__init__.py
atomic_p2p/communication/command.py
atomic_p2p/communication/handler.py
atomic_p2p/communication/packet.py
atomic_p2p/logging/__init__.py
atomic_p2p/logging/formatters.py
atomic_p2p/logging/handlers.py
atomic_p2p/manager/__init__.py
atomic_p2p/manager/process.py
atomic_p2p/manager/thread.py
atomic_p2p/mixin/__init__.py
atomic_p2p/mixin/commandable.py
atomic_p2p/mixin/handleable.py
atomic_p2p/mixin/authenticator/__init__.py
atomic_p2p/mixin/authenticator/default_authenticator.py
atomic_p2p/mixin/topology/__init__.py
atomic_p2p/mixin/topology/lan/__init__.py
atomic_p2p/mixin/topology/lan/handler/__init__.py
atomic_p2p/mixin/topology/lan/handler/ack_new_member.py
atomic_p2p/mixin/topology/lan/handler/check_join.py
atomic_p2p/mixin/topology/lan/handler/disconnect.py
atomic_p2p/mixin/topology/lan/handler/join.py
atomic_p2p/mixin/topology/lan/handler/new_member.py
atomic_p2p/peer/__init__.py
atomic_p2p/peer/command.py
atomic_p2p/peer/communication.py
atomic_p2p/peer/peer.py
atomic_p2p/peer/process_peer.py
atomic_p2p/peer/thread_peer.py
atomic_p2p/peer/entity/__init__.py
atomic_p2p/peer/entity/peer_info.py
atomic_p2p/peer/entity/peer_status.py
atomic_p2p/peer/monitor/__init__.py
atomic_p2p/peer/monitor/command.py
atomic_p2p/peer/monitor/communication.py
atomic_p2p/utils/__init__.py
atomic_p2p/utils/dns_resolver.py
atomic_p2p/utils/security.py