Metadata-Version: 2.1
Name: AtomicP2P
Version: 0.0.6
Summary: A P2P framework which base on multi-process and threading with DNS syncing mechanism.
Home-page: https://github.com/YuntechNet/AtomicP2P
Author: Clooooode
Author-email: jackey8616@gmail.com
License: GNU Lesser General Public License v2.1
Download-URL: https://github.com/YuntechNet/AtomicP2P/releases/tag/0.0.6
Keywords: peer-to-peer,P2P,p2p,distribute,HA,High-Availability
Platform: UNKNOWN
Classifier: Development Status :: 3 - Alpha
Classifier: Intended Audience :: Developers
Classifier: License :: OSI Approved :: GNU Lesser General Public License v2 or later (LGPLv2+)
Classifier: Programming Language :: Python :: 3.5
Classifier: Programming Language :: Python :: 3.6
Requires-Python: >=3.5
